test/__init__.py
test/test_ping_api.py
test/test_price.py
test/test_prices.py
test/test_prices_api.py
test/test_product.py
test/test_products.py
test/test_provider.py
test/test_providers.py
test/test_service.py
test/test_services.py
vantage/__init__.py
vantage/api_client.py
vantage/configuration.py
vantage/rest.py
vantage/api/__init__.py
vantage/api/ping_api.py
vantage/api/prices_api.py
vantage/models/__init__.py
vantage/models/price.py
vantage/models/prices.py
vantage/models/product.py
vantage/models/products.py
vantage/models/provider.py
vantage/models/providers.py
vantage/models/service.py
vantage/models/services.py
vantage_client-0.0.2.dist-info/METADATA
vantage_client-0.0.2.dist-info/WHEEL
vantage_client-0.0.2.dist-info/top_level.txt
vantage_client-0.0.2.dist-info/RECORD
