Metadata-Version: 2.1
Name: vantage-client
Version: 0.0.2
Summary: Vantage
Home-page: UNKNOWN
Author: UNKNOWN
Author-email: support@vantage.sh
License: UNKNOWN
Keywords: Swagger,Vantage
Platform: UNKNOWN
Requires-Dist: certifi (>=2017.4.17)
Requires-Dist: python-dateutil (>=2.1)
Requires-Dist: six (>=1.10)
Requires-Dist: urllib3 (>=1.23)
